async_moip/__init__.py
async_moip-0.0.4.dist-info/METADATA
async_moip-0.0.4.dist-info/RECORD
async_moip-0.0.4.dist-info/WHEEL
async_moip-0.0.4.dist-info/top_level.txt
