Metadata-Version: 2.1
Name: async-moip
Version: 0.0.4
Summary: Moip API wrapper for asyncio/aiohttp
Home-page: https://github.com/jersobh/async-moip
Author: jersobh
Author-email: jersobh@gmail.com
License: UNKNOWN
Platform: UNKNOWN
Classifier: Programming Language :: Python :: 3
Classifier: License :: OSI Approved :: MIT License
Classifier: Operating System :: OS Independent
